Metadata-Version: 2.1
Name: Mensajes-Nikk
Version: 7.0
Summary: Un paquete para saludar y despedir
Author: Nicolas Roman Blanco
Author-email: nicolasromanblanco@gmail.com
Classifier: Environment :: Console
Classifier: Intended Audience :: Developers
Classifier: License :: OSI Approved :: MIT License
Classifier: Operating System :: OS Independent
Classifier: Programming Language :: Python
Classifier: Programming Language :: Python :: 3.11
Classifier: Topic :: Utilities
License-File: LICENSE
Requires-Dist: numpy (>=1.23.0)
